cligames/__init__.py
cligames/cli.py
cligames/version.py
cligames/boards/__init__.py
cligames/boards/board.py
cligames/boards/connect4.py
cligames/boards/tictactoe.py
cligames/players/__init__.py
cligames/players/computer.py
cligames/players/human.py
cligames/players/player.py
cligames-0.2.1.dist-info/licenses/LICENSE
cligames-0.2.1.dist-info/METADATA
cligames-0.2.1.dist-info/WHEEL
cligames-0.2.1.dist-info/entry_points.txt
cligames-0.2.1.dist-info/top_level.txt
cligames-0.2.1.dist-info/RECORD
