Metadata-Version: 2.4
Name: cligames
Version: 0.2.1
Author: Thomas Brier
License-File: LICENSE
Requires-Dist: typer
Requires-Dist: rich
Dynamic: author
Dynamic: description
Dynamic: description-content-type
Dynamic: license-file
Dynamic: requires-dist
